git_check_rebase/__init__.py
git_check_rebase/check_rebase_meta.py
git_check_rebase/compare_commits.py
git_check_rebase/compare_ranges.py
git_check_rebase/gcr_jira.py
git_check_rebase/html_table_view.py
git_check_rebase/parse_issues.py
git_check_rebase/simple_git.py
git_check_rebase/span.py
git_check_rebase/text_table_view.py
git_check_rebase/viewable.py
git_check_rebase-0.5.data/scripts/git-check-rebase
git_check_rebase-0.5.dist-info/METADATA
git_check_rebase-0.5.dist-info/WHEEL
git_check_rebase-0.5.dist-info/top_level.txt
git_check_rebase-0.5.dist-info/RECORD
