Metadata-Version: 2.1
Name: git-check-rebase
Version: 0.5
Summary: Some useful scripts to operate track history and patch changes during rebases.
Home-page: https://gitlab.com/vsementsov/git-check-rebase
Author: Vladimir Sementsov-Ogievskiy
Author-email: vsementsov@yandex-team.ru
License: MIT
Project-URL: Docs, https://git-check-rebase.readthedocs.io/en/latest/
Requires-Dist: tabulate
Requires-Dist: termcolor
